MANIFEST.in
README.rst
setup.py
MyCapytain/__init__.py
MyCapytain/errors.py
MyCapytain.egg-info/PKG-INFO
MyCapytain.egg-info/SOURCES.txt
MyCapytain.egg-info/dependency_links.txt
MyCapytain.egg-info/not-zip-safe
MyCapytain.egg-info/requires.txt
MyCapytain.egg-info/top_level.txt
MyCapytain/common/__init__.py
MyCapytain/common/base.py
MyCapytain/common/constants.py
MyCapytain/common/metadata.py
MyCapytain/common/reference/__init__.py
MyCapytain/common/reference/_base.py
MyCapytain/common/reference/_capitains_cts.py
MyCapytain/common/reference/_dts_1.py
MyCapytain/common/utils/__init__.py
MyCapytain/common/utils/_generic.py
MyCapytain/common/utils/_graph.py
MyCapytain/common/utils/_http.py
MyCapytain/common/utils/_json_ld.py
MyCapytain/common/utils/dts.py
MyCapytain/common/utils/xml.py
MyCapytain/resolvers/__init__.py
MyCapytain/resolvers/prototypes.py
MyCapytain/resolvers/utils.py
MyCapytain/resolvers/cts/__init__.py
MyCapytain/resolvers/cts/api.py
MyCapytain/resolvers/cts/local.py
MyCapytain/resolvers/dts/__init__.py
MyCapytain/resolvers/dts/api_v1.py
MyCapytain/resources/__init__.py
MyCapytain/resources/collections/__init__.py
MyCapytain/resources/collections/cts.py
MyCapytain/resources/collections/dts/__init__.py
MyCapytain/resources/collections/dts/_base.py
MyCapytain/resources/collections/dts/_resolver.py
MyCapytain/resources/prototypes/__init__.py
MyCapytain/resources/prototypes/metadata.py
MyCapytain/resources/prototypes/text.py
MyCapytain/resources/prototypes/cts/__init__.py
MyCapytain/resources/prototypes/cts/inventory.py
MyCapytain/resources/prototypes/cts/text.py
MyCapytain/resources/texts/__init__.py
MyCapytain/resources/texts/base/__init__.py
MyCapytain/resources/texts/base/tei.py
MyCapytain/resources/texts/local/__init__.py
MyCapytain/resources/texts/local/capitains/__init__.py
MyCapytain/resources/texts/local/capitains/cts.py
MyCapytain/resources/texts/remote/__init__.py
MyCapytain/resources/texts/remote/cts.py
MyCapytain/resources/texts/remote/dts/__init__.py
MyCapytain/resources/texts/remote/dts/_resolver_v1.py
MyCapytain/retrievers/__init__.py
MyCapytain/retrievers/cts5.py
MyCapytain/retrievers/prototypes.py
MyCapytain/retrievers/dts/__init__.py