Metadata-Version: 2.1
Name: MyCapytain
Version: 3.0.1
Summary: Library for CTS APIs and CapiTainS guidelines in Python
Home-page: http://github.com/Capitains/MyCapytain
Author: Thibault Clerice
Author-email: leponteineptique@gmail.com
License: Mozilla Public License Version 2.0
Platform: UNKNOWN
Classifier: Development Status :: 5 - Production/Stable
Classifier: Intended Audience :: Developers
Classifier: Intended Audience :: Education
Classifier: Intended Audience :: Information Technology
Classifier: Intended Audience :: Science/Research
Classifier: License :: OSI Approved :: GNU General Public License v3 or later (GPLv3+)
Classifier: Topic :: Software Development :: Libraries
Classifier: Topic :: Text Processing :: Markup :: XML
Classifier: Topic :: Text Processing :: General
Provides-Extra: DOC
